dotpromptz/__init__.py
dotpromptz/dotprompt.py
dotpromptz/errors.py
dotpromptz/helpers.py
dotpromptz/models.py
dotpromptz/parse.py
dotpromptz/picoschema.py
dotpromptz/py.typed
dotpromptz/resolvers.py
dotpromptz/typing.py
dotpromptz/util.py
dotpromptz/adapters/__init__.py
dotpromptz/adapters/openai.py
dotpromptz/stores/__init__.py
dotpromptz/stores/_dir_async.py
dotpromptz/stores/_dir_sync.py
dotpromptz/stores/_io.py
dotpromptz/stores/_testutils.py
dotpromptz/stores/_typing.py
dotpromptz-0.1.5.dist-info/METADATA
dotpromptz-0.1.5.dist-info/WHEEL
dotpromptz-0.1.5.dist-info/licenses/LICENSE
dotpromptz-0.1.5.dist-info/RECORD
