Metadata-Version: 2.4
Name: dotpromptz
Version: 0.1.5
Summary: Dotpromptz is a language-neutral executable prompt template file format for Generative AI.
Author: Google
License-Expression: Apache-2.0
License-File: LICENSE
Classifier: Development Status :: 3 - Alpha
Classifier: Environment :: Console
Classifier: Environment :: Web Environment
Classifier: Intended Audience :: Developers
Classifier: Operating System :: OS Independent
Classifier: Programming Language :: Python
Classifier: Programming Language :: Python :: 3 :: Only
Classifier: Programming Language :: Python :: 3.10
Classifier: Programming Language :: Python :: 3.11
Classifier: Programming Language :: Python :: 3.12
Classifier: Programming Language :: Python :: 3.13
Classifier: Programming Language :: Python :: 3.14
Classifier: Topic :: Scientific/Engineering :: Artificial Intelligence
Classifier: Topic :: Software Development :: Libraries
Requires-Python: >=3.10
Requires-Dist: aiofiles>=24.1.0
Requires-Dist: anyio>=4.9.0
Requires-Dist: dotpromptz-handlebars>=0.1.8
Requires-Dist: pydantic[email]>=2.10.6
Requires-Dist: pyyaml>=6.0.2
Requires-Dist: structlog>=25.2.0
Requires-Dist: types-aiofiles>=24.1.0.20250326
Requires-Dist: types-pyyaml>=6.0.12.20241230
